junglead/__init__.py
junglead/datetime_util.py
junglead/email_util.py
junglead/json_encoder.py
junglead/logger_util.py
junglead/regex_util.py
junglead/snowflake_util.py
junglead/model/__init__.py
junglead/model/extend_datetime.py
junglead/model/extend_decimal.py
junglead-2.4.dist-info/LICENSE
junglead-2.4.dist-info/METADATA
junglead-2.4.dist-info/WHEEL
junglead-2.4.dist-info/top_level.txt
junglead-2.4.dist-info/RECORD
