Metadata-Version: 2.1
Name: junglead
Version: 2.4
Summary: Junglead common util by Python version.
Home-page: https://gitee.com/shwfed-tsd/junglead-common-python
Author: Gary Wang
Author-email: wangyijun@shwfed.com
Project-URL: Bug Tracker, https://gitee.com/shwfed-tsd/junglead-common-python/issues
Classifier: Programming Language :: Python :: 3
Classifier: License :: OSI Approved :: MIT License
Classifier: Operating System :: OS Independent
Requires-Python: >=3
License-File: LICENSE
Requires-Dist: setuptools
Requires-Dist: wheel
